Findex_GUI-0.2.18.dist-info/DESCRIPTION.rst
Findex_GUI-0.2.18.dist-info/METADATA
Findex_GUI-0.2.18.dist-info/RECORD
Findex_GUI-0.2.18.dist-info/WHEEL
Findex_GUI-0.2.18.dist-info/entry_points.txt
Findex_GUI-0.2.18.dist-info/metadata.json
Findex_GUI-0.2.18.dist-info/top_level.txt
findex_gui/__init__.py
findex_gui/main.py
findex_gui/web.py
findex_gui/bin/__init__.py
findex_gui/bin/config.py
findex_gui/bin/misc.py
findex_gui/bin/startup.py
findex_gui/bin/utils.py
findex_gui/controllers/__init__.py
findex_gui/controllers/helpers.py
findex_gui/controllers/themes.py
findex_gui/controllers/admin/__init__.py
findex_gui/controllers/admin/api.py
findex_gui/controllers/admin/routes.py
findex_gui/controllers/auth/README.md
findex_gui/controllers/auth/__init__.py
findex_gui/controllers/auth/auth.py
findex_gui/controllers/auth/permissions.py
findex_gui/controllers/browse/__init__.py
findex_gui/controllers/browse/api.py
findex_gui/controllers/browse/browse.py
findex_gui/controllers/browse/converters.py
findex_gui/controllers/browse/routes.py
findex_gui/controllers/meta_imdb/__init__.py
findex_gui/controllers/meta_imdb/api.py
findex_gui/controllers/meta_imdb/controller.py
findex_gui/controllers/meta_imdb/converters.py
findex_gui/controllers/meta_imdb/populate.py
findex_gui/controllers/meta_imdb/routes.py
findex_gui/controllers/options/__init__.py
findex_gui/controllers/options/options.py
findex_gui/controllers/posts/__init__.py
findex_gui/controllers/posts/api.py
findex_gui/controllers/posts/posts.py
findex_gui/controllers/relay/__init__.py
findex_gui/controllers/relay/relay.py
findex_gui/controllers/relay/routes.py
findex_gui/controllers/resources/__init__.py
findex_gui/controllers/resources/api.py
findex_gui/controllers/resources/forms.py
findex_gui/controllers/resources/resources.py
findex_gui/controllers/routes/__init__.py
findex_gui/controllers/routes/before_request.py
findex_gui/controllers/routes/errors.py
findex_gui/controllers/routes/static.py
findex_gui/controllers/search/__init__.py
findex_gui/controllers/search/api.py
findex_gui/controllers/search/converters.py
findex_gui/controllers/search/routes.py
findex_gui/controllers/search/search.py
findex_gui/controllers/session/__init__.py
