Metadata-Version: 2.0
Name: Findex-GUI
Version: 0.2.18
Summary: Multi-purpose search engine for various protocols.
Home-page: https://github.com/skftn/findex-gui
Author: Sander Ferdinand
Author-email: sa.ferdinand@gmail.com
License: MIT
Keywords: findex ftp http smb crawler search engine
Platform: UNKNOWN
Classifier: Development Status :: 3 - Alpha
Classifier: Environment :: Console
Classifier: Environment :: Web Environment
Classifier: Framework :: Flask
Classifier: Framework :: Pytest
Classifier: Intended Audience :: Information Technology
Classifier: Intended Audience :: Science/Research
Classifier: Natural Language :: English
Classifier: License :: OSI Approved :: MIT License
Classifier: Operating System :: POSIX :: Linux
Classifier: Programming Language :: Python :: 3.5
Classifier: Topic :: Security
Requires-Dist: IPy (==0.83)
Requires-Dist: click
Requires-Dist: findex-common
Requires-Dist: flask (==0.12)
Requires-Dist: flask-auth (==0.85)
Requires-Dist: flask-babel
Requires-Dist: flask-wtf (==0.14.2)
Requires-Dist: furl (==0.5.7)
Requires-Dist: gevent (==1.2.1)
Requires-Dist: humanfriendly (==3.2)
Requires-Dist: jinja2 (==2.9.5)
Requires-Dist: markupsafe
Requires-Dist: psycopg2 (==2.7.1)
Requires-Dist: pysocks
Requires-Dist: python-magic
Requires-Dist: requests (==2.13.0)
Requires-Dist: sqlalchemy (>=1.1.6)
Requires-Dist: sqlalchemy-utils (>=0.32.13)
Requires-Dist: sqlalchemy-zdb (>=0.1.0)
